sispo/__init__.py
sispo/__main__.py
sispo/sispo.py
sispo/compression/__init__.py
sispo/compression/compression.py
sispo/plugins/plugins.py
sispo/reconstruction/__init__.py
sispo/reconstruction/openmvg.py
sispo/reconstruction/openmvs.py
sispo/reconstruction/reconstruction.py
sispo/reconstruction/utils.py
sispo/sim/__init__.py
sispo/sim/cb.py
sispo/sim/compositor.py
sispo/sim/render.py
sispo/sim/sc.py
sispo/sim/sim.py
sispo/sim/sssb.py
sispo/sim/starcat.py
sispo/sim/stars.py
sispo/sim/utils.py
sispo-0.2.0.dist-info/LICENSE
sispo-0.2.0.dist-info/METADATA
sispo-0.2.0.dist-info/WHEEL
sispo-0.2.0.dist-info/entry_points.txt
sispo-0.2.0.dist-info/top_level.txt
sispo-0.2.0.dist-info/RECORD
