Metadata-Version: 2.1
Name: sispo
Version: 0.2.0
Summary: Space Imaging Simulator for Proximity Operations
Home-page: https://github.com/YgabrielsY/sispo
Author: Gabriel J. Schwarzkopf, Mihkel Pajusalu
Author-email: UNKNOWN
License: GNU General Public License v3
Platform: Windows
Classifier: Programming Language :: Python :: 3.7
Classifier: License :: OSI Approved :: GNU General Public License v3 (GPLv3)
Classifier: Operating System :: Microsoft :: Windows :: Windows 10
Classifier: Operating System :: POSIX :: Linux
Classifier: Development Status :: 2 - Pre-Alpha
Classifier: Natural Language :: English
Requires-Dist: astropy
Requires-Dist: numpy
Requires-Dist: opencv-contrib-python
Requires-Dist: openexr
Requires-Dist: orekit
Requires-Dist: mathutils
